pygfn0-0.0.3.dist-info/RECORD
pygfn0-0.0.3.dist-info/WHEEL
pygfn0-0.0.3.dist-info/METADATA
pygfn0-0.0.3.dist-info/licenses/LICENSE
pygfn0/__init__.py
pygfn0/_pygfn0lib.cpython-311-darwin.so
pygfn0/_pygfn0.py
pygfn0/.dylibs/libgfortran.5.dylib
pygfn0/.dylibs/libquadmath.0.dylib
pygfn0/.dylibs/libgcc_s.1.1.dylib
