Metadata-Version: 2.2
Name: pygfn0
Version: 0.0.3
Summary: A Python Library for GFN-FF.
Author-Email: Liu Gaoyong <liugaoyong_88@163.com>
License:                     GNU GENERAL PUBLIC LICENSE
Classifier: Development Status :: 5 - Production/Stable
Classifier: Environment :: Console
Classifier: Environment :: Other Environment
Classifier: Intended Audience :: Education
Classifier: Intended Audience :: Science/Research
Classifier: License :: OSI Approved :: GNU General Public License (GPL)
Classifier: Natural Language :: English
Classifier: Operating System :: MacOS :: MacOS X
Classifier: Operating System :: Microsoft :: Windows
Classifier: Operating System :: POSIX :: Linux
Classifier: Programming Language :: Python
Classifier: Topic :: Scientific/Engineering :: Chemistry
Classifier: Topic :: Software Development :: Libraries
Project-URL: homepage, https://github.com/LiuGaoyong/PyGFNFF
Project-URL: repository, https://github.com/LiuGaoyong/PyGFNFF
Requires-Python: >=3.9
Requires-Dist: ase
Requires-Dist: numpy
Requires-Dist: typing_extensions
